setup.py
zbuild/globals.py
zbuild/version.py
zbuild/zbuild.py
zbuild.egg-info/PKG-INFO
zbuild.egg-info/SOURCES.txt
zbuild.egg-info/dependency_links.txt
zbuild.egg-info/entry_points.txt
zbuild.egg-info/not-zip-safe
zbuild.egg-info/top_level.txt
zbuild/finder/__init__.py
zbuild/finder/files.py
zbuild/generator/__init__.py
zbuild/generator/_generate_modules.py
zbuild/generator/_load_source.py
zbuild/generator/_parse.py
zbuild/generator/project_files_generator.py
zbuild/generator/project_files/__init__.py
zbuild/generator/project_files/cmake_generator.py
zbuild/generator/project_files/cmake/__init__.py
zbuild/generator/project_files/cmake/generate_file.py
zbuild/log/__init__.py
zbuild/log/logger.py
zbuild/module/__init__.py
zbuild/module/module_obj.py
zbuild/data/cmake_files/common.cmake
zbuild/data/cmake_files/configure.cmake
zbuild/data/cmake_files/utils.cmake
zbuild/data/cmake_files/version.cmake
zbuild/data/cmake_files/platforms/linux.cmake
zbuild/data/cmake_files/platforms/windows.cmake