Metadata-Version: 1.2
Name: zbuild
Version: 0.0.1
Summary: Build myself sysytem.
Home-page: https://pypi.org/
Author: Zeit
Author-email: zeit.13@outlook.com
Maintainer: Zeit
Maintainer-email: zeit.13@outlook.com
License: GPLv3
Platform: any
Classifier: Programming Language :: Python :: 3.5
Classifier: Topic :: Scientific/Engineering :: Visualization
